changeform_actions/__init__.py
changeform_actions/admin.py
changeform_actions/apps.py
changeform_actions/forms.py
changeform_actions/urls.py
changeform_actions/views.py
changeform_actions/templates/admin/actions_for_changeform.html
changeform_actions/templates/admin/change_form.html
changeform_actions/templatetags/changeform_actions.py
django_admin_changeform_actions-0.5.4.dist-info/METADATA
django_admin_changeform_actions-0.5.4.dist-info/WHEEL
django_admin_changeform_actions-0.5.4.dist-info/licenses/LICENSE
django_admin_changeform_actions-0.5.4.dist-info/RECORD
