Metadata-Version: 2.4
Name: django-admin-changeform-actions
Version: 0.5.4
Summary: Reuse model admin changelist actions on changeform pages
Project-URL: Homepage, https://github.com/cb109/django-admin-changeform-actions
Author-email: Christoph Buelter <buelter.christoph@gmail.com>
License-Expression: MIT
License-File: LICENSE
Requires-Python: >=3.8
Requires-Dist: django>=3.2
